Workbook

Sheet 1º Acerto
A1: 1º Fechamento ano 2024
A3: Linha Januária | D3: Linha Coração | G3: Faturamento
A4: Total linha: | B4: 12240 | D4: Total linha: | E4: 10140 | H4: Januária | I4: Chapada | J4: Salinas | K4: Coração | L4: B. Minas | M4: Bahia | N4: Moc Globo
A5: Diárias (hotel + refeições) | B5: 860 | D5: Diárias (hotel + refeições) | E5: 540 | G5: Total Faturado por linha | H5: =B4 -> 12240 | I5: =B12 -> 10213 | J5: =B20 -> 8340 | K5: =E4 -> 10140 | L5: =B28 -> 10552 | M5: =E12 -> 10788 | N5: =E20 -> 13460
A6: Combustível | B6: 1814 | D6: Combustível | E6: 493 | G6: Total faturamento Linhas Petrina | H6: =H8*0.4 -> 30293.2
A7: Comissão motorista | B7: 287 | D7: Comissão motorista | E7: 274 | G7: Total fatuamento Linhas Rossiny | H7: =H8*0.6 -> 45439.8
A8: Comissão Iltair + Etien | B8: 247 | D8: Comissão Iltair | E8: 202 | G8: Total Faturamento Geral | H8: =SUM(H5:N5) -> 75733
A9: Notas | B9: 3669 | D9: Notas | E9: 4749 | G9: Qtidade mesas por linha | H9: 132 | I9: 91 | J9: 71 | K9: 82 | L9: 97 | M9: 93 | N9: 98
A11: Linha Chapada | D11: Linha Bahia | G11: Despesas | L11: %
A12: Total linha: | B12: 10213 | D12: Total linha: | E12: 10788 | G12: Total Diárias | H12: =E5+B5+B13+B21+E13+E21+B29 -> 3910 | L12: =H12/H18 -> 0.09058332
A13: Diárias (hotel + refeições) | B13: 670 | D13: Diárias (hotel + refeições) | E13: 540 | G13: Total Combustível | H13: =E6+B6+B14+B22+B30+E14+E22 -> 5638 | L13: =H13/H18 -> 0.13061605
A14: Combustível | B14: 750 | D14: Combustível | E14: 603 | G14: Total comissão motorista | H14: =E7+B7+B15+B23+B31+E15+E23 -> 1612 | L14: =H14/H18 -> 0.037345348
A15: Comissão motorista | B15: 264 | D15: Comissão motorista | E15: 290 | G15: Total comissão Iltair + Etiene | H15: =E8+B8+B16+B24+B32+E16+E24 -> 1622 | L15: =H15/H18 -> 0.037577019
A16: Comissão Iltair | B16: 204 | D16: Comissão Iltair | E16: 215 | G16: Total Notas | H16: =E9+B9+B17+B25+B33+E17+E25 -> 30382.68 | L16: =H16/H22 -> 0.70387826
A17: Notas | B17: 4291.68 | D17: Notas | E17: 2771 | G17: Total outras despesas | H17: =E36 -> 0 | L17: =H17/H23 -> 0
G18: Total Geral Despesas | H18: =H17+H16+H15+H14+H13+H12 -> 43164.68
A19: Linha Salinas | D19: Linha Moc Globo
A20: Total linha: | B20: 8340 | D20: Total linha: | E20: 13460 | G20: Lucro
A21: Diárias (hotel + refeições) | B21: 670 | D21: Diárias (hotel + refeições) | E21: 90 | G21: Faturamento Geral | H21: =H8 -> 75733
A22: Combustível | B22: 451 | D22: Combustível | E22: 842 | G22: Despesa Geral | H22: =H18 -> 43164.68
A23: Comissão motorista | B23: 217 | D23: Comissão motorista | G23: Lucro Geral | H23: =H21-H22 -> 32568.32
A24: Comissão Iltair + Etiene | B24: 167 | D24: Comissão Iltair | E24: 376 | G24: Lucro Petrina | H24: =H23*0.4 -> 13027.328
A25: Notas | B25: 5616 | D25: Notas | E25: 1823 | G25: Lucro Rossiny | H25: =H23*0.6 -> 19540.992
A27: Linha Bonito Minas | D27: Outras Despesas
A28: Total linha: | B28: 10552 | D28: Descrição | E28: Valor | G28: Margem líquida (lucro/ faturam) | H28: =H23/H21 -> 0.43004133
A29: Diárias (hotel + refeições) | B29: 540 | D29: Panos 3/4 | E29: 1918 | G29: Total mesas locadas | H29: =SUM(H9:N9) -> 664
A30: Combustível | B30: 685 | D30: Pneus F350 6/10 | E30: 361.58 | G30: Faturamento por mesa | H30: =H21/H29 -> 114.05572
A31: Comissão motorista | B31: 280 | D31: Osorio placas ? | E31: 450 | G31: Lucro por mesa | H31: =H23/H29 -> 49.048675
A32: Comissão Iltair | B32: 211 | D32: Simples nacional jan 24 | E32: 50.87 | G32: Despesa por mesa | H32: =H22/H29 -> 65.007048
A33: Notas | B33: 7463 | D33: Contadora jan 24 | E33: 290
D34: FGTS + INSS jan 24 | E34: 2162.92
D35: Bonus Iltair
D36: Total outra despesas

Sheet 2º Acerto 
A1: 2º Fechamento ano 2024
A3: Linha Januária | D3: Linha Coração | G3: Faturamento
A4: Total linha: | B4: 15908 | D4: Total linha: | E4: 8852 | H4: Januária | I4: Chapada | J4: Salinas | K4: Coração | L4: B. Minas | M4: Bahia | N4: Moc Globo
A5: Diárias (hotel + refeições) | B5: 1280 | D5: Diárias (hotel + refeições) | E5: 540 | G5: Total Faturado por linha | H5: =B4 -> 15908 | I5: =B12 -> 13477 | J5: =B20 -> 2040 | K5: =E4 -> 8852 | L5: =B28 -> 0 | M5: =E12 -> 12420 | N5: =E20 -> 11285
A6: Combustível | B6: 1516 | D6: Combustível | E6: 542 | G6: Total faturamento Linhas Petrina | H6: =H8*0.4 -> 25592.8
A7: Comissão motorista | B7: 394 | D7: Comissão motorista | E7: 234 | G7: Total fatuamento Linhas Rossiny | H7: =H8*0.6 -> 38389.2
A8: Comissão Iltair | B8: 318 | D8: Comissão Iltair | E8: 177 | G8: Total Faturamento Geral | H8: =SUM(H5:N5) -> 63982
A9: Notas | B9: 1448 | D9: Notas | E9: 2474 | G9: Qtidade mesas por linha | H9: 132 | I9: 95 | J9: 71 | K9: 84 | L9: 100 | M9: 93 | N9: 96
A11: Linha Chapada | D11: Linha Bahia | G11: Despesas | L11: %
A12: Total linha: | B12: 13477 | D12: Total linha: | E12: 12420 | G12: Total Diárias | H12: =E5+B5+B13+B21+E13+E21+B29 -> 3790 | L12: =H12/H18 -> 0.1173323
A13: Diárias (hotel + refeições) | B13: 860 | D13: Diárias (hotel + refeições) | E13: 540 | G13: Total Combustível | H13: =E6+B6+B14+B22+B30+E14+E22 -> 4880 | L13: =H13/H18 -> 0.15107695
A14: Combustível | B14: 946 | D14: Combustível | E14: 868 | G14: Total comissão motorista | H14: =E7+B7+B15+B23+B31+E15+E23 -> 1356 | L14: =H14/H18 -> 0.041979579
A15: Comissão motorista | B15: 350 | D15: Comissão motorista | E15: 331 | G15: Total comissão Iltair | H15: =E8+B8+B16+B24+B32+E16+E24 -> 1359 | L15: =H15/H18 -> 0.042072454
A16: Comissão Iltair | B16: 270 | D16: Comissão Iltair | E16: 248 | G16: Total Notas | H16: =E9+B9+B17+B25+B33+E17+E25 -> 14212 | L16: =H16/H22 -> 0.43998066
A17: Notas | B17: 5195 | D17: Notas | E17: 1548 | G17: Total outras despesas | H17: =E37 -> 6704.42 | L17: =H17/H23 -> 0.21162554
G18: Total Geral Despesas | H18: =H17+H16+H15+H14+H13+H12 -> 32301.42
A19: Linha Salinas | D19: Linha Moc Globo
A20: Total linha: | B20: 2040 | D20: Total linha: | E20: 11285 | G20: Lucro
A21: Diárias (hotel + refeições) | B21: 480 | D21: Diárias (hotel + refeições) | E21: 90 | G21: Faturamento Geral | H21: =H8 -> 63982
A22: Combustível | D22: Combustível | E22: 1008 | G22: Despesa Geral | H22: =H18 -> 32301.42
A23: Comissão motorista | B23: 47 | D23: Comissão motorista | G23: Lucro Geral | H23: =H21-H22 -> 31680.58
A24: Comissão Iltair | B24: 40 | D24: Comissão Iltair | E24: 306 | G24: Lucro Petrina | H24: =H23*0.4 -> 12672.232
A25: Notas | D25: Notas | E25: 3547 | G25: Lucro Rossiny | H25: =H23*0.6 -> 19008.348
A27: Linha Bonito Minas | D27: Outras Despesas
A28: Total linha: | D28: Descrição | E28: Valor | G28: Margem líquida (lucro/ faturam) | H28: =H23/H21 -> 0.49514832
A29: Diárias (hotel + refeições) | D29: Panos 4/4 | E29: 1918 | G29: Total mesas locadas | H29: =SUM(H9:N9) -> 671
A30: Combustível | D30: Pneus F350 7/10 | E30: 361.58 | G30: Faturamento por mesa | H30: =H21/H29 -> 95.353204
A31: Comissão motorista | D31: Andressa pagamento | G31: Lucro por mesa | H31: =H23/H29 -> 47.213979
A32: Comissão Iltair | D32: Simples nacional fev 24 | E32: 2331 | G32: Despesa por mesa | H32: =H22/H29 -> 48.139225
A33: Notas | D33: Contadora fev 24 | E33: 310
D34: FGTS + INSS fev 24 | E34: 1783.84
D35: Doc carros Licenc e 1 parc IPVA
D36: Ficheiro uberaba
D37: Total outra despesas | E37: =SUM(E29:E36) -> 6704.42

Sheet 3º Acerto
A1: 3º Fechamento ano 2024
A3: Linha Januária | D3: Linha Coração | G3: Faturamento
A4: Total linha: | B4: 12286 | D4: Total linha: | E4: 7363 | H4: Januária | I4: Chapada | J4: Salinas | K4: Coração | L4: B. Minas | M4: Bahia | N4: Moc Globo
A5: Diárias (hotel + refeições) | B5: 830 | D5: Diárias (hotel + refeições) | E5: 540 | G5: Total Faturado por linha | H5: =B4 -> 12286 | I5: =B12 -> 9849 | J5: =B20 -> 9569 | K5: =E4 -> 7363 | L5: =B28 -> 6388 | M5: =E12 -> 9110 | N5: =E20 -> 10517
A6: Combustível | B6: 1307 | D6: Combustível | E6: 950.5 | G6: Total faturamento Linhas Petrina | H6: =H8*0.4 -> 26032.8
A7: Comissão motorista | B7: 305 | D7: Comissão motorista | E7: 177 | G7: Total fatuamento Linhas Rossiny | H7: =H8*0.6 -> 39049.2
A8: Comissão Iltair | B8: 245 | D8: Comissão Iltair | E8: 147 | G8: Total Faturamento Geral | H8: =SUM(H5:N5) -> 65082
A9: Notas | B9: 1572 | D9: Notas | E9: 3886.88 | G9: Qtidade mesas por linha | H9: 134 | I9: 95 | J9: 72 | K9: 84 | L9: 102 | M9: 92 | N9: 95
A11: Linha Chapada | D11: Linha Bahia | G11: Despesas | L11: %
A12: Total linha: | B12: 9849 | D12: Total linha: | E12: 9110 | G12: Total Diárias | H12: =E5+B5+B13+B21+E13+E21+B29 -> 4130 | L12: =H12/H18 -> 0.068458239
A13: Diárias (hotel + refeições) | B13: 1050 | D13: Diárias (hotel + refeições) | E13: 540 | G13: Total Combustível | H13: =E6+B6+B14+B22+B30+E14+E22 -> 5634.5 | L13: =H13/H18 -> 0.093396598
A14: Combustível | B14: 654 | D14: Combustível | E14: 757 | G14: Total comissão motorista | H14: =E7+B7+B15+B23+B31+E15+E23 -> 1380 | L14: =H14/H18 -> 0.022874666
A15: Comissão motorista | B15: 245 | D15: Comissão motorista | E15: 235 | G15: Total comissão Iltair | H15: =E8+B8+B16+B24+B32+E16+E24 -> 1372 | L15: =H15/H18 -> 0.022742059
A16: Comissão Iltair | B16: 197 | D16: Comissão Iltair | E16: 182 | G16: Total Notas | H16: =E9+B9+B17+B25+B33+E17+E25 -> 25545.97 | L16: =H16/H22 -> 0.42344604
A17: Notas | B17: 4969 | D17: Notas | E17: 1163 | G17: Total outras despesas | H17: =E41 -> 22266.28 | L17: =H17/H23 -> 4.6844328
G18: Total Geral Despesas | H18: =H17+H16+H15+H14+H13+H12 -> 60328.75
A19: Linha Salinas | D19: Linha Moc Globo
A20: Total linha: | B20: 9569 | D20: Total linha: | E20: 10517 | G20: Lucro
A21: Diárias (hotel + refeições) | B21: 540 | D21: Diárias (hotel + refeições) | E21: 90 | G21: Faturamento Geral | H21: =H8 -> 65082
A22: Combustível | B22: 700 | D22: Combustível | E22: 1016 | G22: Despesa Geral | H22: =H18 -> 60328.75
A23: Comissão motorista | B23: 250 | D23: Comissão motorista | G23: Lucro Geral | H23: =H21-H22 -> 4753.25
A24: Comissão Iltair | B24: 191 | D24: Comissão Iltair | E24: 283 | G24: Lucro Petrina | H24: =H23*0.4 -> 1901.3
A25: Notas | B25: 5417.09 | D25: Notas | E25: 4693 | G25: Lucro Rossiny | H25: =H23*0.6 -> 2851.95
A27: Linha Bonito Minas | D27: Outras Despesas
A28: Total linha: | B28: 6388 | D28: Descrição | E28: Valor | G28: Margem líquida (lucro/ faturam) | H28: =H23/H21 -> 0.073034787
A29: Diárias (hotel + refeições) | B29: 540 | D29: Materiais Vilson 1/2 | E29: 1750 | G29: Total mesas locadas | H29: =SUM(H9:N9) -> 674
A30: Combustível | B30: 250 | D30: 2 Pneus silverado | E30: 2627.48 | G30: Faturamento por mesa | H30: =H21/H29 -> 96.560831
A31: Comissão motorista | B31: 168 | D31: Pneus F350 8/10 | E31: 361.58 | G31: Lucro por mesa | H31: =H23/H29 -> 7.0522997
A32: Comissão Iltair | B32: 127 | D32: Caixa de marcha F350 | E32: 8200 | G32: Despesa por mesa | H32: =H22/H29 -> 89.508531
A33: Notas | B33: 3845 | D33: Contadora março 24 | E33: 310
D34: Tacos 1/3 | E34: 1680
D35: Panos Tahís 1/4 | E35: 1929
D36: simple nacional março 24 | E36: 0
D37: Pneu F350 nova | E37: 1770
D38: FGTS + INSS março 24 | E38: 1868.22
D39: 1 pneu F350 nova | E39: 1770
D40: Doc carros 2 parc IPVA
D41: Total outra despesas | E41: =SUM(E29:E40) -> 22266.28

Sheet 4º Acerto
A1: 4º Fechamento ano 2024
A3: Linha Januária | D3: Linha Coração | G3: Faturamento
A4: Total linha: | B4: 9452 | D4: Total linha: | E4: 6624 | H4: Januária | I4: Chapada | J4: Salinas | K4: Coração | L4: B. Minas | M4: Bahia | N4: Moc Globo
A5: Diárias (hotel + refeições) | B5: 800 | D5: Diárias (hotel + refeições) | E5: 540 | G5: Total Faturado por linha | H5: =B4 -> 9452 | I5: =B12 -> 12668 | J5: =B20 -> 4985 | K5: =E4 -> 6624 | L5: =B28 -> 6588 | M5: =E12 -> 7080 | N5: =E20 -> 10090
A6: Combustível | B6: 1005 | D6: Combustível | E6: 700 | G6: Total faturamento Linhas Petrina | H6: =H8*0.4 -> 22994.8
A7: Comissão motorista | B7: 230 | D7: Comissão motorista | E7: 162 | G7: Total fatuamento Linhas Rossiny | H7: =H8*0.6 -> 34492.2
A8: Comissão Iltair + Etien | B8: 189 | D8: Comissão Iltair | E8: 132 | G8: Total Faturamento Geral | H8: =SUM(H5:N5) -> 57487
A9: Notas | B9: 4502 | D9: Notas | E9: 2324 | G9: Qtidade mesas por linha | H9: 136 | I9: 93 | J9: 72 | K9: 85 | L9: 103 | M9: 92 | N9: 93
A11: Linha Chapada | D11: Linha Bahia | G11: Despesas | L11: %
A12: Total linha: | B12: 12668 | D12: Total linha: | E12: 7080 | G12: Total Diárias | H12: =E5+B5+B13+B21+E13+E21+B29 -> 3720 | L12: =H12/H18 -> 0.082681513
A13: Diárias (hotel + refeições) | B13: 700 | D13: Diárias (hotel + refeições) | E13: 510 | G13: Total Combustível | H13: =E6+B6+B14+B22+B30+E14+E22 -> 4936 | L13: =H13/H18 -> 0.10970859
A14: Combustível | B14: 1300 | D14: Combustível | E14: 430 | G14: Total comissão motorista | H14: =E7+B7+B15+B23+B31+E15+E23 -> 1467 | L14: =H14/H18 -> 0.032605855
A15: Comissão motorista | B15: 321 | D15: Comissão motorista | E15: 185 | G15: Total comissão Iltair | H15: =E8+B8+B16+B24+B32+E16+E24 -> 947 | L15: =H15/H18 -> 0.021048224
A16: Comissão Iltair | B16: 254 | D16: Comissão Iltair | E16: 140 | G16: Total Notas | H16: =E9+B9+B17+B25+B33+E17+E25 -> 20640 | L16: =H16/H22 -> 0.45874904
A17: Notas | B17: 5246 | D17: Notas | E17: 440 | G17: Total outras despesas | H17: =E42 -> 13281.92 | L17: =H17/H23 -> 1.062972
G18: Total Geral Despesas | H18: =H17+H16+H15+H14+H13+H12 -> 44991.92
A19: Linha Salinas | D19: Linha Moc Globo
A20: Total linha: | B20: 4985 | D20: Total linha: | E20: 10090 | G20: Lucro
A21: Diárias (hotel + refeições) | B21: 540 | D21: Diárias (hotel + refeições) | E21: 90 | G21: Faturamento Geral | H21: =H8 -> 57487
A22: Combustível | B22: 746 | D22: Combustível | E22: 305 | G22: Despesa Geral | H22: =H18 -> 44991.92
A23: Comissão motorista | B23: 111 | D23: Comissão motorista | E23: 290 | G23: Lucro Geral | H23: =H21-H22 -> 12495.08
A24: Comissão Iltair + Etiene | B24: 100 | D24: Comissão Iltair | G24: Lucro Petrina | H24: =H23*0.4 -> 4998.032
A25: Notas | B25: 2729 | D25: Notas | E25: 3836 | G25: Lucro Rossiny | H25: =H23*0.6 -> 7497.048
A27: Linha Bonito Minas | D27: Outras Despesas
A28: Total linha: | B28: 6588 | D28: Descrição | E28: Valor | G28: Margem líquida (lucro/ faturam) | H28: =H23/H21 -> 0.21735488
A29: Diárias (hotel + refeições) | B29: 540 | D29: Diferencial peças | E29: 1288 | G29: Total mesas locadas | H29: =SUM(H9:N9) -> 674
A30: Combustível | B30: 450 | D30: Bonus Iltair | E30: 200 | G30: Faturamento por mesa | H30: =H21/H29 -> 85.292285
A31: Comissão motorista | B31: 168 | D31: Pneus F350 9/10 | E31: 361.58 | G31: Lucro por mesa | H31: =H23/H29 -> 18.538694
A32: Comissão Iltair | B32: 132 | D32: Materiais Vilson 2/2 | E32: 1750 | G32: Despesa por mesa | H32: =H22/H29 -> 66.753591
A33: Notas | B33: 1563 | D33: Contadora abril 24 | E33: 310
D34: Tacos 2/3 | E34: 1680
D35: Panos Thaís 2/4 | E35: 1929
D36: Doc carro 3 parc IPVA
D37: Simples Nacional abril 24 | E37: 1868.94
D38: FGTS + INSS abril 24 | E38: 1894.4
D39: Pagamento Isadora | E39: 200
D40: Alteração firma
D41: Pagamento andressa | E41: 1800
D42: Total outra despesas | E42: =SUM(E29:E41) -> 13281.92

Sheet 5º Acerto
A1: 5º Fechamento
A3: Linha Januária | D3: Linha Coração | G3: Faturamento
A4: Total linha: | B4: 9679 | D4: Total linha: | E4: 8735 | H4: Januária | I4: Chapada | J4: Salinas | K4: Coração | L4: B. Minas | M4: Bahia | N4: Moc Globo
A5: Diárias (hotel + refeições) | B5: 800 | D5: Diárias (hotel + refeições) | E5: 540 | G5: Total Faturado por linha | H5: =B4 -> 9679 | I5: =B12 -> 9868 | J5: =B20 -> 7558 | K5: =E4 -> 8735 | L5: =B28 -> 6767 | M5: =E12 -> 7811 | N5: =E20 -> 11300
A6: Combustível | B6: 450 | D6: Combustível | E6: 502 | G6: Total faturamento Linhas Petrina | H6: =H8*0.4 -> 24687.2
A7: Comissão motorista | B7: 253 | D7: Comissão motorista | E7: 231 | G7: Total fatuamento Linhas Rossiny | H7: =H8*0.6 -> 37030.8
A8: Comissão Iltair | B8: 194 | D8: Comissão Iltair | E8: 174 | G8: Total Faturamento Geral | H8: =SUM(H5:N5) -> 61718
A9: Notas | B9: 2252 | D9: Notas | E9: 3399 | G9: Qtidade mesas por linha | H9: 137 | I9: 93 | J9: 73 | K9: 85 | L9: 103 | M9: 89 | N9: 92
A11: Linha Chapada | D11: Linha Bahia | G11: Despesas | L11: %
A12: Total linha: | B12: 9868 | D12: Total linha: | E12: 7811 | G12: Total Diárias | H12: =E5+B5+B13+B21+E13+E21+B29 -> 3750 | L12: =H12/H18 -> 0.092466017
A13: Diárias (hotel + refeições) | B13: 700 | D13: Diárias (hotel + refeições) | E13: 540 | G13: Total Combustível | H13: =E6+B6+B14+B22+B30+E14+E22 -> 3282 | L13: =H13/H18 -> 0.080926258
A14: Combustível | B14: 500 | D14: Combustível | E14: 589 | G14: Total comissão motorista | H14: =E7+B7+B15+B23+B31+E15+E23 -> 1622 | L14: =H14/H18 -> 0.039994635
A15: Comissão motorista | B15: 260 | D15: Comissão motorista | E15: 200 | G15: Total comissão Iltair | H15: =E8+B8+B16+B24+B32+E16+E24 -> 1082 | L15: =H15/H18 -> 0.026679528
A16: Comissão Iltair | B16: 197 | D16: Comissão Iltair | E16: 156 | G16: Total Notas | H16: =E9+B9+B17+B25+B33+E17+E25 -> 22174.5 | L16: =H16/H22 -> 0.54677005
A17: Notas | B17: 5187 | D17: Notas | E17: 1272 | G17: Total outras despesas | H17: =E39 -> 8644.94 | L17: =H17/H23 -> 0.40850162
G18: Total Geral Despesas | H18: =H17+H16+H15+H14+H13+H12 -> 40555.44
A19: Linha Salinas | D19: Linha Moc Globo
A20: Total linha: | B20: 7558 | D20: Total linha: | E20: 11300 | G20: Lucro
A21: Diárias (hotel + refeições) | B21: 540 | D21: Diárias (hotel + refeições) | E21: 90 | G21: Faturamento Geral | H21: =H8 -> 61718
A22: Combustível | B22: 841 | D22: Combustível | G22: Despesa Geral | H22: =H18 -> 40555.44
A23: Comissão motorista | B23: 185 | D23: Comissão motorista | E23: 318 | G23: Lucro Geral | H23: =H21-H22 -> 21162.56
A24: Comissão Iltair | B24: 226 | D24: Comissão Iltair | G24: Lucro Petrina | H24: =H23*0.4 -> 8465.024
A25: Notas | B25: 280 | D25: Notas | E25: 5680 | G25: Lucro Rossiny | H25: =H23*0.6 -> 12697.536
A27: Linha Bonito Minas | D27: Outras Despesas
A28: Total linha: | B28: 6767 | D28: Descrição | E28: Valor | G28: Margem líquida (lucro/ faturam) | H28: =H23/H21 -> 0.34289121
A29: Diárias (hotel + refeições) | B29: 540 | D29: Pneus silverado (23 maio) | E29: 2000 | G29: Total mesas locadas | H29: =SUM(H9:N9) -> 672
A30: Combustível | B30: 400 | D30: Panos Thaís 3/4 | E30: 1929 | G30: Faturamento por mesa | H30: =H21/H29 -> 91.842262
A31: Comissão motorista | B31: 175 | D31: Pneus F350 10/10 | E31: 361.58 | G31: Lucro por mesa | H31: =H23/H29 -> 31.491905
A32: Comissão Iltair | B32: 135 | D32: Simples nacional maio 24 | E32: 0 | G32: Despesa por mesa | H32: =H22/H29 -> 60.350357
A33: Notas | B33: 4104.5 | D33: Contadora maio 24 | E33: 310
D34: Tacos | E34: 1680
D35: FGTS + INSS maio 24 | E35: 1784.36
D36: Alteração firma | E36: 580 | G36: verificar
D37: Direção hidr. Silverado 1/3
D38: Pg Andressa
D39: Total outra despesas | E39: =SUM(E29:E38) -> 8644.94

Sheet 6º Acerto
A1: 6º Fechamento ano 2024
A3: Linha Januária | D3: Linha Coração | G3: Faturamento
A4: Total linha: | B4: 10235 | D4: Total linha: | E4: 6794 | H4: Januária | I4: Chapada | J4: Salinas | K4: Coração | L4: B. Minas | M4: Bahia | N4: Moc Globo
A5: Diárias (hotel + refeições) | B5: 800 | D5: Diárias (hotel + refeições) | E5: 540 | G5: Total Faturado por linha | H5: =B4 -> 10235 | I5: =B12 -> 12238 | J5: =B20 -> 8059 | K5: =E4 -> 6794 | L5: =B28 -> 6557 | M5: =E12 -> 9294 | N5: =E20 -> 12698
A6: Combustível | B6: 733 | D6: Combustível | E6: 350 | G6: Total faturamento Linhas Petrina | H6: =H8*0.4 -> 26350
A7: Comissão motorista | B7: 261 | D7: Comissão motorista | E7: 178 | G7: Total fatuamento Linhas Rossiny | H7: =H8*0.6 -> 39525
A8: Comissão Iltair | B8: 205 | D8: Comissão Iltair | E8: 135 | G8: Total Faturamento Geral | H8: =SUM(H5:N5) -> 65875
A9: Notas | B9: 3340 | D9: Notas | E9: 3186 | G9: Qtidade mesas por linha | H9: 137 | I9: 94 | J9: 71 | K9: 86 | L9: 104 | M9: 88 | N9: 92
A11: Linha Chapada | D11: Linha Bahia | G11: Despesas | L11: %
A12: Total linha: | B12: 12238 | D12: Total linha: | E12: 9294 | G12: Total Diárias | H12: =E5+B5+B13+B21+E13+E21+B29 -> 3850 | L12: =H12/H18 -> 0.10141988
A13: Diárias (hotel + refeições) | B13: 700 | D13: Diárias (hotel + refeições) | E13: 540 | G13: Total Combustível | H13: =E6+B6+B14+B22+B30+E14+E22 -> 5087 | L13: =H13/H18 -> 0.13400595
A14: Combustível | B14: 1322 | D14: Combustível | E14: 869 | G14: Total comissão motorista | H14: =E7+B7+B15+B23+B31+E15+E23 -> 1710 | L14: =H14/H18 -> 0.045046232
A15: Comissão motorista | B15: 307 | D15: Comissão motorista | E15: 237 | G15: Total comissão Iltair | H15: =E8+B8+B16+B24+B32+E16+E24 -> 1061 | L15: =H15/H18 -> 0.027949738
A16: Comissão Iltair | B16: 244 | D16: Comissão Iltair | E16: 185 | G16: Total Notas | H16: =E9+B9+B17+B25+B33+E17+E25 -> 26253 | L16: =H16/H22 -> 0.6915782
A17: Notas | B17: 2975 | D17: Notas | E17: 2025 | G17: Total outras despesas | H17: =E38 -> 0 | L17: =H17/H23 -> 0
G18: Total Geral Despesas | H18: =H17+H16+H15+H14+H13+H12 -> 37961
A19: Linha Salinas | D19: Linha Moc Globo
A20: Total linha: | B20: 8059 | D20: Total linha: | E20: 12698 | G20: Lucro
A21: Diárias (hotel + refeições) | B21: 640 | D21: Diárias (hotel + refeições) | E21: 90 | G21: Faturamento Geral | H21: =H8 -> 65875
A22: Combustível | B22: 803 | D22: Combustível | E22: 610 | G22: Despesa Geral | H22: =H18 -> 37961
A23: Comissão motorista | B23: 198 | D23: Comissão motorista | E23: 360 | G23: Lucro Geral | H23: =H21-H22 -> 27914
A24: Comissão Iltair | B24: 161 | D24: Comissão Iltair | G24: Lucro Petrina | H24: =H23*0.4 -> 11165.6
A25: Notas | B25: 5025 | D25: Notas | E25: 6992 | G25: Lucro Rossiny | H25: =H23*0.6 -> 16748.4
A27: Linha Bonito Minas | D27: Outras Despesas
A28: Total linha: | B28: 6557 | D28: Descrição | E28: Valor | G28: Margem líquida (lucro/ faturam) | H28: =H23/H21 -> 0.42374194
A29: Diárias (hotel + refeições) | B29: 540 | D29: Panos Thaís 4/4 | E29: 1929 | G29: Total mesas locadas | H29: =SUM(H9:N9) -> 672
A30: Combustível | B30: 400 | D30: Pneus F350 nova | E30: 2520 | G30: Faturamento por mesa | H30: =H21/H29 -> 98.028274
A31: Comissão motorista | B31: 169 | D31: Taco pg em 30/06 | G31: Lucro por mesa | H31: =H23/H29 -> 41.53869
A32: Comissão Iltair | B32: 131 | D32: Simples nacional junho 24 | E32: 1592.96 | G32: Despesa por mesa | H32: =H22/H29 -> 56.489583
A33: Notas | B33: 2710 | D33: Contadora junho 24 | E33: 310
D34: FGTS + INSS junho 24 | E34: 1880.37
D36: Pneus F350 nova | E36: 2520
D37: Bicos injetores
D38: Total outra despesas

Sheet 7º Acerto
A1: 7º Fechamento ano 2024
A3: Linha Januária | D3: Linha Coração | G3: Faturamento
A4: Total linha: | B4: 9397 | D4: Total linha: | E4: 10361 | H4: Januária | I4: Chapada | J4: Salinas | K4: Coração | L4: B. Minas | M4: Bahia | N4: Moc Globo
A5: Diárias (hotel + refeições) | B5: 830 | D5: Diárias (hotel + refeições) | E5: 700 | G5: Total Faturado por linha | H5: =B4 -> 9397 | I5: =B12 -> 10132 | J5: =B20 -> 7148 | K5: =E4 -> 10361 | L5: =B28 -> 6770 | M5: =E12 -> 7425 | N5: =E20 -> 9865
A6: Combustível | B6: 739 | D6: Combustível | E6: 800 | G6: Total faturamento Linhas Petrina | H6: =H8*0.4 -> 24439.2
A7: Comissão motorista | B7: 235 | D7: Comissão motorista | E7: 266 | G7: Total fatuamento Linhas Rossiny | H7: =H8*0.6 -> 36658.8
A8: Comissão Iltair + Etien | B8: 187 | D8: Comissão Iltair | E8: 207 | G8: Total Faturamento Geral | H8: =SUM(H5:N5) -> 61098
A9: Notas | B9: 5177 | D9: Notas | E9: 2518 | G9: Qtidade mesas por linha | H9: 133 | I9: 95 | J9: 71 | K9: 86 | L9: 104 | M9: 87 | N9: 90
A11: Linha Chapada | D11: Linha Bahia | G11: Despesas | L11: %
A12: Total linha: | B12: 10132 | D12: Total linha: | E12: 7425 | G12: Total Diárias | H12: =E5+B5+B13+B21+E13+E21+B29 -> 3650 | L12: =H12/H18 -> 0.087858466
A13: Diárias (hotel + refeições) | B13: 380 | D13: Diárias (hotel + refeições) | E13: 570 | G13: Total Combustível | H13: =E6+B6+B14+B22+B30+E14+E22 -> 5445 | L13: =H13/H18 -> 0.13106557
A14: Combustível | B14: 1427 | D14: Combustível | E14: 200 | G14: Total comissão motorista | H14: =E7+B7+B15+B23+B31+E15+E23 -> 1560 | L14: =H14/H18 -> 0.037550467
A15: Comissão motorista | B15: 249 | D15: Comissão motorista | E15: 200 | G15: Total comissão Iltair | H15: =E8+B8+B16+B24+B32+E16+E24 -> 1023 | L15: =H15/H18 -> 0.024624441
A16: Comissão Iltair | B16: 202 | D16: Comissão Iltair | E16: 149 | G16: Total Notas | H16: =E9+B9+B17+B25+B33+E17+E25 -> 23049.5 | L16: =H16/H22 -> 0.55482019
A17: Notas | B17: 2976.5 | D17: Notas | E17: 2747 | G17: Total outras despesas | H17: =E39 -> 6816.59 | L17: =H17/H23 -> 0.34860496
G18: Total Geral Despesas | H18: =H17+H16+H15+H14+H13+H12 -> 41544.09
A19: Linha Salinas | D19: Linha Moc Globo
A20: Total linha: | B20: 7148 | D20: Total linha: | E20: 9865 | G20: Lucro
A21: Diárias (hotel + refeições) | B21: 540 | D21: Diárias (hotel + refeições) | E21: 90 | G21: Faturamento Geral | H21: =H8 -> 61098
A22: Combustível | B22: 1574 | D22: Combustível | E22: 305 | G22: Despesa Geral | H22: =H18 -> 41544.09
A23: Comissão motorista | B23: 151 | D23: Comissão motorista | E23: 284 | G23: Lucro Geral | H23: =H21-H22 -> 19553.91
A24: Comissão Iltair | B24: 143 | G24: Lucro Petrina | H24: =H23*0.4 -> 7821.564
A25: Notas | B25: 1754 | D25: Notas | E25: 4396 | G25: Lucro Rossiny | H25: =H23*0.6 -> 11732.346
A27: Linha Bonito Minas | D27: Outras Despesas
A28: Total linha: | B28: 6770 | D28: Descrição | E28: Valor | G28: Margem líquida (lucro/ faturam) | H28: =H23/H21 -> 0.32004174
A29: Diárias (hotel + refeições) | B29: 540 | D29: Panos Thaís 3/3 | G29: Total mesas locadas | H29: =SUM(H9:N9) -> 666
A30: Combustível | B30: 400 | D30: Mat. Vilson 1/2 | E30: 2587 | G30: Faturamento por mesa | H30: =H21/H29 -> 91.738739
A31: Comissão motorista | B31: 175 | D31: Taco | G31: Lucro por mesa | H31: =H23/H29 -> 29.360225
A32: Comissão Iltair | B32: 135 | D32: Simples nacional julho 24 | E32: 1099.22 | G32: Despesa por mesa | H32: =H22/H29 -> 62.378514
A33: Notas | B33: 3481 | D33: Contadora julho 24 | E33: 310
D34: FGTS + INSS julho 24 | E34: 1880.37
D35: Taxas devolver bicos (ver) | E35: 940
D36: Direção hidr. Silverado 3/3
D39: Total outra despesas | E39: =SUM(E29:E38) -> 6816.59

Sheet 8º Acerto
A1: 8º Fechamento ano 2024
A3: Linha Januária | D3: Linha Coração | G3: Faturamento
A4: Total linha: | B4: 9563 | D4: Total linha: | E4: 6110 | H4: Januária | I4: Chapada | J4: Salinas | K4: Coração | L4: B. Minas | M4: Bahia | N4: Moc Globo
A5: Diárias (hotel + refeições) | B5: 660 | D5: Diárias (hotel + refeições) | E5: 480 | G5: Total Faturado por linha | H5: =B4 -> 9563 | I5: =B12 -> 16145 | J5: =B20 -> 7565 | K5: =E4 -> 6110 | L5: =B28 -> 6577 | M5: =E12 -> 9085 | N5: =E20 -> 10238
A6: Combustível | B6: 789 | D6: Combustível | E6: 570 | G6: Total faturamento Linhas Petrina | H6: =H8*0.4 -> 26113.2
A7: Comissão motorista | B7: 244 | D7: Comissão motorista | E7: 152 | G7: Total fatuamento Linhas Rossiny | H7: =H8*0.6 -> 39169.8
A8: Comissão Iltair | B8: 192 | D8: Comissão Iltair | E8: 122 | G8: Total Faturamento Geral | H8: =SUM(H5:N5) -> 65283
A9: Notas | B9: 4752 | D9: Notas | E9: 2465 | G9: Qtidade mesas por linha | H9: 134 | I9: 99 | J9: 73 | K9: 85 | L9: 103 | M9: 87 | N9: 88
A11: Linha Chapada | D11: Linha Bahia | G11: Despesas | L11: %
A12: Total linha: | B12: 16145 | D12: Total linha: | E12: 9085 | G12: Total Diárias | H12: =E5+B5+B13+B21+E13+E21+B29 -> 4370 | L12: =H12/H18 -> 0.072999261
A13: Diárias (hotel + refeições) | B13: 1160 | D13: Diárias (hotel + refeições) | E13: 670 | G13: Total Combustível | H13: =E6+B6+B14+B22+B30+E14+E22 -> 5750 | L13: =H13/H18 -> 0.096051659
A14: Combustível | B14: 1112 | D14: Combustível | E14: 1052 | G14: Total comissão motorista | H14: =E7+B7+B15+B23+B31+E15+E23 -> 1656 | L14: =H14/H18 -> 0.027662878
A15: Comissão motorista | B15: 416 | D15: Comissão motorista | E15: 221 | G15: Total comissão Iltair | H15: =E8+B8+B16+B24+B32+E16+E24 -> 1100 | L15: =H15/H18 -> 0.0183751
A16: Comissão Iltair | B16: 323 | D16: Comissão Iltair | E16: 182 | G16: Total Notas | H16: =E9+B9+B17+B25+B33+E17+E25 -> 28019 | L16: =H16/H22 -> 0.4680472
A17: Notas | B17: 7382 | D17: Notas | E17: 2997 | G17: Total outras despesas | H17: =E40 -> 18968.62 | L17: =H17/H23 -> 3.5001458
G18: Total Geral Despesas | H18: =H17+H16+H15+H14+H13+H12 -> 59863.62
A19: Linha Salinas | D19: Linha Moc Globo
A20: Total linha: | B20: 7565 | D20: Total linha: | E20: 10238 | G20: Lucro
A21: Diárias (hotel + refeições) | B21: 660 | D21: Diárias (hotel + refeições) | E21: 120 | G21: Faturamento Geral | H21: =H8 -> 65283
A22: Combustível | B22: 750 | D22: Combustível | E22: 687 | G22: Despesa Geral | H22: =H18 -> 59863.62
A23: Comissão motorista | B23: 185 | D23: Comissão motorista | E23: 283 | G23: Lucro Geral | H23: =H21-H22 -> 5419.38
A24: Comissão Iltair | B24: 150 | D24: Comissão Iltair | G24: Lucro Petrina | H24: =H23*0.4 -> 2167.752
A25: Notas | B25: 3480 | D25: Notas | E25: 3191 | G25: Lucro Rossiny | H25: =H23*0.6 -> 3251.628
A27: Linha Bonito Minas | D27: Outras Despesas
A28: Total linha: | B28: 6577 | D28: Descrição | E28: Valor | G28: Margem líquida (lucro/ faturam) | H28: =H23/H21 -> 0.083013648
A29: Diárias (hotel + refeições) | B29: 620 | D29: (RECISAO ETINE) | E29: 2624 | G29: Total mesas locadas | H29: =SUM(H9:N9) -> 669
A30: Combustível | B30: 790 | D30: Mat. Vilson 2/2 | E30: 2580 | G30: Faturamento por mesa | H30: =H21/H29 -> 97.58296
A31: Comissão motorista | B31: 155 | D31: Tacos 1/3 | E31: 1260 | G31: Lucro por mesa | H31: =H23/H29 -> 8.1007175
A32: Comissão Iltair | B32: 131 | D32: Simples nacional ago 24 | E32: 1141.26 | G32: Despesa por mesa | H32: =H22/H29 -> 89.482242
A33: Notas | B33: 3752 | D33: Contadora ago 24 | E33: 310
D34: FGTS + INSS ago 24 | E34: 1784.36
D35: Compra diverplay | E35: 7869
D36: Recuperação bico | E36: 1200
D37: Comissão Iltair | E37: 200
D40: Total outra despesas | E40: =SUM(E29:E39) -> 18968.62

Sheet 9º Acerto
A1: 9º Fechamento ano 2024
A3: Linha Januária | D3: Linha Coração | G3: Faturamento
A4: Total linha: | B4: 8054 | D4: Total linha: | E4: 6110 | H4: Januária | I4: Chapada | J4: Salinas | K4: Coração | L4: B. Minas | M4: Bahia | N4: Moc Globo
A5: Diárias (hotel + refeições) | B5: 760 | D5: Diárias (hotel + refeições) | E5: 580 | G5: Total Faturado por linha | H5: =B4 -> 8054 | I5: =B12 -> 13361 | J5: =B20 -> 5230 | K5: =E4 -> 6110 | L5: =B28 -> 4770 | M5: =E12 -> 8952 | N5: =E20 -> 11124
A6: Combustível | B6: 589 | D6: Combustível | E6: 957 | G6: Total faturamento Linhas Petrina | H6: =H8*0.4 -> 23040.4
A7: Comissão motorista | B7: 201 | D7: Comissão motorista | E7: 138 | G7: Total fatuamento Linhas Rossiny | H7: =H8*0.6 -> 34560.6
A8: Comissão Iltair | B8: 161 | D8: Comissão Iltair | E8: 122 | G8: Total Faturamento Geral | H8: =SUM(H5:N5) -> 57601
A9: Notas | B9: 3570 | D9: Notas | E9: 2014 | G9: Qtidade mesas por linha | H9: 134 | I9: 100 | J9: 75 | K9: 85 | L9: 103 | M9: 86 | N9: 87
A11: Linha Chapada | D11: Linha Bahia-036 | G11: Despesas | L11: %
A12: Total linha: | B12: 13361 | D12: Total linha: | E12: 8952 | G12: Total Diárias | H12: =E5+B5+B13+B21+E13+E21+B29 -> 4220 | L12: =H12/H18 -> 0.11278842
A13: Diárias (hotel + refeições) | B13: 940 | D13: Diárias (hotel + refeições) | E13: 620 | G13: Total Combustível | H13: =E6+B6+B14+B22+B30+E14+E22 -> 5499 | L13: =H13/H18 -> 0.14697239
A14: Combustível | B14: 1427 | D14: Combustível | E14: 602 | G14: Total comissão motorista | H14: =E7+B7+B15+B23+B31+E15+E23 -> 1437 | L14: =H14/H18 -> 0.038406861
A15: Comissão motorista | B15: 330 | D15: Comissão motorista | E15: 232 | G15: Total comissão Iltair | H15: =E8+B8+B16+B24+B32+E16+E24 -> 923 | L15: =H15/H18 -> 0.024669125
A16: Comissão Iltair | B16: 261 | D16: Comissão Iltair | E16: 179 | G16: Total Notas | H16: =E9+B9+B17+B25+B33+E17+E25 -> 19735 | L16: =H16/H22 -> 0.52745957
A17: Notas | B17: 7062 | D17: Notas | E17: 1597 | G17: Total outras despesas | H17: =E39 -> 5601.19 | L17: =H17/H23 -> 0.27748156
G18: Total Geral Despesas | H18: =H17+H16+H15+H14+H13+H12 -> 37415.19
A19: Linha Salinas-037 | D19: Linha Moc Globo
A20: Total linha: | B20: 5230 | D20: Total linha: | E20: 11124 | G20: Lucro
A21: Diárias (hotel + refeições) | B21: 620 | D21: Diárias (hotel + refeições) | E21: 120 | G21: Faturamento Geral | H21: =H8 -> 57601
A22: Combustível | B22: 563 | D22: Combustível | E22: 711 | G22: Despesa Geral | H22: =H18 -> 37415.19
A23: Comissão motorista | B23: 121 | D23: Comissão motorista | E23: 309 | G23: Lucro Geral | H23: =H21-H22 -> 20185.81
A24: Comissão Iltair | B24: 105 | D24: Comissão Iltair | G24: Lucro Petrina | H24: =H23*0.4 -> 8074.324
A25: Notas | B25: 1629 | D25: Notas | E25: 3188 | G25: Lucro Rossiny | H25: =H23*0.6 -> 12111.486
A27: Linha Bonito Minas | D27: Outras Despesas
A28: Total linha: | B28: 4770 | D28: Descrição | E28: Valor | G28: Margem líquida (lucro/ faturam) | H28: =H23/H21 -> 0.35044201
A29: Diárias (hotel + refeições) | B29: 580 | D29: Panos Thais | G29: Total mesas locadas | H29: =SUM(H9:N9) -> 670
A30: Combustível | B30: 650 | D30: Mat. Vilson | G30: Faturamento por mesa | H30: =H21/H29 -> 85.971642
A31: Comissão motorista | B31: 106 | D31: Taco 2/3 | E31: 1260 | G31: Lucro por mesa | H31: =H23/H29 -> 30.128075
A32: Comissão Iltair | B32: 95 | D32: Simples nacional set 24 | E32: 1176.97 | G32: Despesa por mesa | H32: =H22/H29 -> 55.843567
A33: Notas | B33: 675 | D33: Contadora set 24 | E33: 310
D34: FGTS + INSS set 24 | E34: 1854.22
D35: Ficheiros 1/2 | E35: 700
D38: Bonus Iltair | E38: 300
D39: Total outra despesas | E39: =SUM(E29:E38) -> 5601.19

Sheet 10º Acerto
A1: 10º Fechamento ano 2024
A3: Linha Januária | D3: Linha Coração | G3: Faturamento
A4: Total linha: | B4: 8102 | D4: Total linha: | E4: 6141 | H4: Januária | I4: Chapada | J4: Salinas | K4: Coração | L4: B. Minas | M4: Bahia | N4: Moc Globo
A5: Diárias (hotel + refeições) | B5: 620 | D5: Diárias (hotel + refeições) | E5: 440 | G5: Total Faturado por linha | H5: =B4 -> 8102 | I5: =B12 -> 11824 | J5: =B20 -> 6190 | K5: =E4 -> 6141 | L5: =B28 -> 6075 | M5: =E12 -> 7550 | N5: =E20 -> 11625
A6: Combustível | B6: 624 | D6: Combustível | E6: 511 | G6: Total faturamento Linhas Petrina | H6: =H8*0.4 -> 23002.8
A7: Comissão motorista | B7: 206 | D7: Comissão motorista | E7: 156 | G7: Total fatuamento Linhas Rossiny | H7: =H8*0.6 -> 34504.2
A8: Comissão Iltair | B8: 162 | D8: Comissão Iltair | E8: 122 | G8: Total Faturamento Geral | H8: =SUM(H5:N5) -> 57507
A9: Notas | B9: 4358 | D9: Notas | E9: 1938 | G9: Qtidade mesas por linha | H9: 132 | I9: 100 | J9: 75 | K9: 87 | L9: 103 | M9: 86 | N9: 87
A11: Linha Chapada | D11: Linha Bahia | G11: Despesas | L11: %
A12: Total linha: | B12: 11824 | D12: Total linha: | E12: 7550 | G12: Total Diárias | H12: =E5+B5+B13+B21+E13+E21+B29 -> 3900 | L12: =H12/H18 -> 0.10424739
A13: Diárias (hotel + refeições) | B13: 800 | D13: Diárias (hotel + refeições) | E13: 580 | G13: Total Combustível | H13: =E6+B6+B14+B22+B30+E14+E22 -> 4953 | L13: =H13/H18 -> 0.13239418
A14: Combustível | B14: 930 | D14: Combustível | E14: 872 | G14: Total comissão motorista | H14: =E7+B7+B15+B23+B31+E15+E23 -> 1461 | L14: =H14/H18 -> 0.039052675
A15: Comissão motorista | B15: 303 | D15: Comissão motorista | E15: 183 | G15: Total comissão Iltair | H15: =E8+B8+B16+B24+B32+E16+E24 -> 916 | L15: =H15/H18 -> 0.024484771
A16: Comissão Iltair | B16: 236 | D16: Comissão Iltair | E16: 151 | G16: Total Notas | H16: =E9+B9+B17+B25+B33+E17+E25 -> 21058 | L16: =H16/H22 -> 0.56288242
A17: Notas | B17: 5509 | D17: Notas | E17: 210 | G17: Total outras despesas | H17: =E39 -> 5123.01 | L17: =H17/H23 -> 0.25492698
G18: Total Geral Despesas | H18: =H17+H16+H15+H14+H13+H12 -> 37411.01
A19: Linha Salinas | D19: Linha Moc Globo
A20: Total linha: | B20: 6190 | D20: Total linha: | E20: 11625 | G20: Lucro
A21: Diárias (hotel + refeições) | B21: 720 | D21: Diárias (hotel + refeições) | E21: 160 | G21: Faturamento Geral | H21: =H8 -> 57507
A22: Combustível | B22: 300 | D22: Combustível | E22: 1016 | G22: Despesa Geral | H22: =H18 -> 37411.01
A23: Comissão motorista | B23: 155 | D23: Comissão motorista | E23: 314 | G23: Lucro Geral | H23: =H21-H22 -> 20095.99
A24: Comissão Iltair | B24: 124 | D24: Comissão Iltair | G24: Lucro Petrina | H24: =H23*0.4 -> 8038.396
A25: Notas | B25: 3678 | D25: Notas | E25: 1548 | G25: Lucro Rossiny | H25: =H23*0.6 -> 12057.594
A27: Linha Bonito Minas | D27: Outras Despesas
A28: Total linha: | B28: 6075 | D28: Descrição | E28: Valor | G28: Margem líquida (lucro/ faturam) | H28: =H23/H21 -> 0.34945294
A29: Diárias (hotel + refeições) | B29: 580 | D29: Panos Thais | G29: Total mesas locadas | H29: =SUM(H9:N9) -> 670
A30: Combustível | B30: 700 | D30: Materiais Vilson 1/2 | E30: 1140 | G30: Faturamento por mesa | H30: =H21/H29 -> 85.831343
A31: Comissão motorista | B31: 144 | D31: Taco 3/3 | E31: 1260 | G31: Lucro por mesa | H31: =H23/H29 -> 29.994015
A32: Comissão Iltair | B32: 121 | D32: S nacional out 24- n teve | G32: Despesa por mesa | H32: =H22/H29 -> 55.837328
A33: Notas | B33: 3817 | D33: Contadora out 24 | E33: 310
D34: FGTS + INSS out 24 | E34: 1713.01
D35: Ficheiros 2/2 | E35: 700
D39: Total outra despesas | E39: =SUM(E29:E38) -> 5123.01

Sheet 11º Acerto
A1: 11º Fechamento ano 2023
A3: Linha Januária | D3: Linha Coração | G3: Faturamento
A4: Total linha: | D4: Total linha: | H4: Januária | I4: Chapada | J4: Salinas | K4: Coração | L4: B. Minas | M4: Bahia | N4: Moc Globo
A5: Diárias (hotel + refeições) | D5: Diárias (hotel + refeições) | G5: Total Faturado por linha | H5: =B4 -> 0 | I5: =B12 -> 0 | J5: =B20 -> 0 | K5: =E4 -> 0 | L5: =B28 -> 0 | M5: =E12 -> 0 | N5: =E20 -> 0
A6: Combustível | D6: Combustível | G6: Total faturamento Linhas Petrina | H6: =H8*0.4 -> 0
A7: Comissão motorista | D7: Comissão motorista | G7: Total fatuamento Linhas Rossiny | H7: =H8*0.6 -> 0
A8: Comissão Iltair | D8: Comissão Iltair | G8: Total Faturamento Geral | H8: =SUM(H5:N5) -> 0
A9: Notas | D9: Notas | G9: Qtidade mesas por linha
A11: Linha Chapada | D11: Linha Bahia | G11: Despesas | L11: %
A12: Total linha: | D12: Total linha: | G12: Total Diárias | H12: =E5+B5+B13+B21+E13+E21+B29 -> 0 | L12: =H12/H18 -> 0
A13: Diárias (hotel + refeições) | D13: Diárias (hotel + refeições) | G13: Total Combustível | H13: =E6+B6+B14+B22+B30+E14+E22 -> 0 | L13: =H13/H18 -> 0
A14: Combustível | D14: Combustível | G14: Total comissão motorista | H14: =E7+B7+B15+B23+B31+E15+E23 -> 0 | L14: =H14/H18 -> 0
A15: Comissão motorista | D15: Comissão motorista | G15: Total comissão Iltair | H15: =E8+B8+B16+B24+B32+E16+E24 -> 0 | L15: =H15/H18 -> 0
A16: Comissão Iltair | D16: Comissão Iltair | G16: Total Notas | H16: =E9+B9+B17+B25+B33+E17+E25 -> 0 | L16: =H16/H22 -> 0
A17: Notas | D17: Notas | G17: Total outras despesas | H17: =E39 -> 7219.83 | L17: =H17/H23 -> -1
G18: Total Geral Despesas | H18: =H17+H16+H15+H14+H13+H12 -> 7219.83
A19: Linha Salinas | D19: Linha Moc Globo
A20: Total linha: | D20: Total linha: | G20: Lucro
A21: Diárias (hotel + refeições) | D21: Diárias (hotel + refeições) | G21: Faturamento Geral | H21: =H8 -> 0
A22: Combustível | D22: Combustível | G22: Despesa Geral | H22: =H18 -> 7219.83
A23: Comissão motorista | D23: Comissão motorista | G23: Lucro Geral | H23: =H21-H22 -> -7219.83
A24: Comissão Iltair | D24: Comissão Iltair | G24: Lucro Petrina | H24: =H23*0.4 -> -2887.932
A25: Notas | D25: Notas | G25: Lucro Rossiny | H25: =H23*0.6 -> -4331.898
A27: Linha Bonito Minas | D27: Outras Despesas
A28: Total linha: | D28: Descrição | E28: Valor | G28: Margem líquida (lucro/ faturam) | H28: =H23/H21 -> #DIV/0!
A29: Diárias (hotel + refeições) | D29: Materiais Vilson 2/2 | E29: 1140 | G29: Total mesas locadas | H29: =SUM(H9:N9) -> 0
A30: Combustível | D30: Materiais Vilson 1/3 | E30: 1600 | G30: Faturamento por mesa | H30: =H21/H29 -> #DIV/0!
A31: Comissão motorista | G31: Lucro por mesa | H31: =H23/H29 -> #DIV/0!
A32: Comissão Iltair | D32: Simp nacional nov 24 | E32: 2338.18 | G32: Despesa por mesa | H32: =H22/H29 -> #DIV/0!
A33: Notas | D33: Contadora nov 24 | E33: 310
D34: FGTS + INSS nov 24 | E34: 1631.65
D38: Bonus Iltair | E38: 200
D39: Total outra despesas | E39: =SUM(E29:E38) -> 7219.83

Sheet 12º Acerto
A1: 12º Fechamento ano 2023
A3: Linha Januária | D3: Linha Coração | G3: Faturamento
A4: Total linha: | D4: Total linha: | H4: Januária | I4: Chapada | J4: Salinas | K4: Coração | L4: B. Minas | M4: Bahia | N4: Moc Globo
A5: Diárias (hotel + refeições) | D5: Diárias (hotel + refeições) | G5: Total Faturado por linha | H5: =B4 -> 0 | I5: =B12 -> 0 | J5: =B20 -> 0 | K5: =E4 -> 0 | L5: =B28 -> 0 | M5: =E12 -> 0 | N5: =E20 -> 0
A6: Combustível | D6: Combustível | G6: Total faturamento Linhas Petrina | H6: =H8*0.4 -> 0
A7: Comissão motorista | D7: Comissão motorista | G7: Total fatuamento Linhas Rossiny | H7: =H8*0.6 -> 0
A8: Comissão Iltair | D8: Comissão Iltair | G8: Total Faturamento Geral | H8: =SUM(H5:N5) -> 0
A9: Notas | D9: Notas | G9: Qtidade mesas por linha
A11: Linha Chapada | D11: Linha Bahia | G11: Despesas | L11: %
A12: Total linha: | D12: Total linha: | G12: Total Diárias | H12: =E5+B5+B13+B21+E13+E21+B29 -> 0 | L12: =H12/H18 -> 0
A13: Diárias (hotel + refeições) | D13: Diárias (hotel + refeições) | G13: Total Combustível | H13: =E6+B6+B14+B22+B30+E14+E22 -> 0 | L13: =H13/H18 -> 0
A14: Combustível | D14: Combustível | G14: Total comissão motorista | H14: =E7+B7+B15+B23+B31+E15+E23 -> 0 | L14: =H14/H18 -> 0
A15: Comissão motorista | D15: Comissão motorista | G15: Total comissão Iltair | H15: =E8+B8+B16+B24+B32+E16+E24 -> 0 | L15: =H15/H18 -> 0
A16: Comissão Iltair | D16: Comissão Iltair | G16: Total Notas | H16: =E9+B9+B17+B25+B33+E17+E25 -> 0 | L16: =H16/H22 -> 0
A17: Notas | D17: Notas | G17: Total outras despesas | H17: =E39 -> 1910 | L17: =H17/H23 -> -1
G18: Total Geral Despesas | H18: =H17+H16+H15+H14+H13+H12 -> 1910
A19: Linha Salinas | D19: Linha Moc Globo
A20: Total linha: | D20: Total linha: | G20: Lucro
A21: Diárias (hotel + refeições) | D21: Diárias (hotel + refeições) | G21: Faturamento Geral | H21: =H8 -> 0
A22: Combustível | D22: Combustível | G22: Despesa Geral | H22: =H18 -> 1910
A23: Comissão motorista | D23: Comissão motorista | G23: Lucro Geral | H23: =H21-H22 -> -1910
A24: Comissão Iltair | D24: Comissão Iltair | G24: Lucro Petrina | H24: =H23*0.4 -> -764
A25: Notas | D25: Notas | G25: Lucro Rossiny | H25: =H23*0.6 -> -1146
A27: Linha Bonito Minas | D27: Outras Despesas
A28: Total linha: | D28: Descrição | E28: Valor | G28: Margem líquida (lucro/ faturam) | H28: =H23/H21 -> #DIV/0!
A29: Diárias (hotel + refeições) | D29: Pano | G29: Total mesas locadas | H29: =SUM(H9:N9) -> 0
A30: Combustível | D30: Materiais Vilson 2/3 | E30: 1600 | G30: Faturamento por mesa | H30: =H21/H29 -> #DIV/0!
A31: Comissão motorista | D31: Taco | G31: Lucro por mesa | H31: =H23/H29 -> #DIV/0!
A32: Comissão Iltair | D32: Simp nacional dez 24 | G32: Despesa por mesa | H32: =H22/H29 -> #DIV/0!
A33: Notas | D33: Contadora dez 24 | E33: 310
D34: FGTS + INSS dez 24
D37: Pneu 4/4
D38: Bonus Iltair
D39: Total outra despesas | E39: =SUM(E29:E38) -> 1910

Sheet Fechamento Ano
A1: Balanço Anual
B3: 1º Acerto | C3: 2º Acerto | D3: 3º Acerto | E3: 4º Acerto | F3: 5º Acerto | G3: 6º Acerto | H3: 7º Acerto | I3: 8º Acerto | J3: 9º Acerto | K3: 10º Acerto | L3: 11º Acerto | M3: 12º Acerto
A4: Faturamento por acerto | B4: ='1º Acerto'!H21 -> 75733 | C4: ='2º Acerto '!H21 -> 63982 | D4: ='3º Acerto'!H21 -> 65082 | E4: ='4º Acerto'!H21 -> 57487 | F4: ='5º Acerto'!H21 -> 61718 | G4: ='6º Acerto'!H21 -> 65875 | H4: ='7º Acerto'!H21 -> 61098 | I4: ='8º Acerto'!H21 -> 65283 | J4: ='9º Acerto'!H21 -> 57601 | K4: ='10º Acerto'!H21 -> 57507 | L4: ='11º Acerto'!H21 -> 0 | M4: ='12º Acerto'!H21 -> 0
A5: Despesa por acerto | B5: ='1º Acerto'!H22 -> 43164.68 | C5: ='2º Acerto '!H22 -> 32301.42 | D5: ='3º Acerto'!H22 -> 60328.75 | E5: ='4º Acerto'!H22 -> 44991.92 | F5: ='5º Acerto'!H22 -> 40555.44 | G5: ='6º Acerto'!H22 -> 37961 | H5: ='7º Acerto'!H22 -> 41544.09 | I5: ='8º Acerto'!H22 -> 59863.62 | J5: ='9º Acerto'!H22 -> 37415.19 | K5: ='10º Acerto'!H22 -> 37411.01 | L5: ='11º Acerto'!H22 -> 7219.83 | M5: ='12º Acerto'!H22 -> 1910
A6: Lucro Total por acerto | B6: ='1º Acerto'!H23 -> 32568.32 | C6: ='2º Acerto '!H23 -> 31680.58 | D6: ='3º Acerto'!H23 -> 4753.25 | E6: ='4º Acerto'!H23 -> 12495.08 | F6: ='5º Acerto'!H23 -> 21162.56 | G6: ='6º Acerto'!H23 -> 27914 | H6: ='7º Acerto'!H23 -> 19553.91 | I6: ='8º Acerto'!H23 -> 5419.38 | J6: ='9º Acerto'!H23 -> 20185.81 | K6: ='10º Acerto'!H23 -> 20095.99 | L6: ='11º Acerto'!H23 -> -7219.83 | M6: ='12º Acerto'!H23 -> -1910
A7: Lucro Petrina por acerto | B7: ='1º Acerto'!H24 -> 13027.328 | C7: ='2º Acerto '!H24 -> 12672.232 | D7: ='3º Acerto'!H24 -> 1901.3 | E7: ='4º Acerto'!H24 -> 4998.032 | F7: ='5º Acerto'!H24 -> 8465.024 | G7: ='6º Acerto'!H24 -> 11165.6 | H7: ='7º Acerto'!H24 -> 7821.564 | I7: ='8º Acerto'!H24 -> 2167.752 | J7: ='9º Acerto'!H24 -> 8074.324 | K7: ='10º Acerto'!H24 -> 8038.396 | L7: ='11º Acerto'!H24 -> -2887.932 | M7: ='12º Acerto'!H24 -> -764
A8: Lucro Rossiny por acerto | B8: ='1º Acerto'!H25 -> 19540.992 | C8: ='2º Acerto '!H25 -> 19008.348 | D8: ='3º Acerto'!H25 -> 2851.95 | E8: ='4º Acerto'!H25 -> 7497.048 | F8: ='5º Acerto'!H25 -> 12697.536 | G8: ='6º Acerto'!H25 -> 16748.4 | H8: ='7º Acerto'!H25 -> 11732.346 | I8: ='8º Acerto'!H25 -> 3251.628 | J8: ='9º Acerto'!H25 -> 12111.486 | K8: ='10º Acerto'!H25 -> 12057.594 | L8: ='11º Acerto'!H25 -> -4331.898 | M8: ='12º Acerto'!H25 -> -1146
D13: FATURAMENTO ANUAL | F13: =SUM(B4:M4) -> 631366 | H13: Margem líquida | I13: =F15/F13 -> 0.29570653 | J13: Lucro /Faturamento
D14: DESPESA ANUAL | F14: =SUM(B5:M5) -> 444666.95 | H14: ROI | I14: =F15/'Patrimonio Rossiny Mãe'!F10 -> 0.14502023 | J14: Lucro liquido / patrimônio
D15: LUCRO TOTAL ANO | F15: =SUM(B6:M6) -> 186699.05 | H15: P/L | I15: ='Patrimonio Rossiny Mãe'!F10/F15 -> 6.8955895 | J15: Patrimônio / Lucro (Verificar)= Qtde anos p retorno
D16: LUCRO ANO PETRINA | F16: =SUM(B7:L7) -> 75443.62 | H16: Ticket medio mesa | I16: =F13/759 -> 831.83926
D17: LUCRO ANO ROSSINY | F17: =SUM(B8:M8) -> 112019.43 | H17: Despesa por mesa | I17: =F14/759 -> 585.85896
H18: Lucro por mesa | I18: =I16-I17 -> 245.9803
D21: XXXXXXXXXX | F21: Januária | G21: Chapada | H21: Salinas | I21: Bonito Minas | J21: Coração | K21: Bahia | L21: Moc
D22: Faturamento anual por linha | F22: =SUM('1º Acerto'!B4,'2º Acerto '!B4,'3º Acerto'!B4,'4º Acerto'!B4,'5º Acerto'!B4,'6º Acerto'!B4,'7º Acerto'!B4,'8º Acerto'!B4,'9º Acerto'!B4,'10º Acerto'!B4,'11º Acerto'!B4,'12º Acerto'!B4) -> 104916 | G22: =SUM('1º Acerto'!B12,'2º Acerto '!B12,'3º Acerto'!B12,'4º Acerto'!B12,'5º Acerto'!B12,'6º Acerto'!B12,'7º Acerto'!B12,'8º Acerto'!B12,'9º Acerto'!B12,'10º Acerto'!B12,'11º Acerto'!B12,'12º Acerto'!B12) -> 119775 | H22: =SUM('1º Acerto'!B20,'2º Acerto '!B20,'3º Acerto'!B20,'4º Acerto'!B20,'5º Acerto'!B20,'6º Acerto'!B20,'7º Acerto'!B20,'8º Acerto'!B20,'9º Acerto'!B20,'10º Acerto'!B20,'11º Acerto'!B20,'12º Acerto'!B20) -> 66684 | I22: =SUM('1º Acerto'!B28,'2º Acerto '!B28,'3º Acerto'!B28,'4º Acerto'!B28,'5º Acerto'!B28,'6º Acerto'!B28,'7º Acerto'!B28,'8º Acerto'!B28,'9º Acerto'!B28,'10º Acerto'!B28,'11º Acerto'!B28,'12º Acerto'!B28) -> 61044 | J22: =SUM('1º Acerto'!E4,'2º Acerto '!E4,'3º Acerto'!E4,'4º Acerto'!E4,'5º Acerto'!E4,'6º Acerto'!E4,'7º Acerto'!E4,'8º Acerto'!E4,'9º Acerto'!E4,'10º Acerto'!E4,'11º Acerto'!E4,'12º Acerto'!E4) -> 77230 | K22: =SUM('1º Acerto'!E12,'2º Acerto '!E12,'3º Acerto'!E12,'4º Acerto'!E12,'5º Acerto'!E12,'6º Acerto'!E12,'7º Acerto'!E12,'8º Acerto'!E12,'9º Acerto'!E12,'10º Acerto'!E12,'11º Acerto'!E12,'12º Acerto'!E12) -> 89515 | L22: =SUM('1º Acerto'!E20,'2º Acerto '!E20,'3º Acerto'!E20,'4º Acerto'!E20,'5º Acerto'!E20,'6º Acerto'!E20,'7º Acerto'!E20,'8º Acerto'!E20,'9º Acerto'!E20,'10º Acerto'!E20,'11º Acerto'!E20,'12º Acerto'!E20) -> 112202
D23: Valor investido
D24: Lucro por linha | F24: =F22*I13 -> 31024.346 | G24: =G22*I13 -> 35418.25 | H24: =H22*I13 -> 19718.894 | I24: =I22*I13 -> 18051.11 | J24: =J22*I13 -> 22837.415 | K24: =K22*I13 -> 26470.17 | L24: =L22*I13 -> 33178.864
D25: P/L por linha

Sheet Patrimonio Rossiny  Mãe
B2: Rossiny | C2: Petrinas
B3: 93 | C3: 111
B4: 62 | C4: 113
B5: 80 | C5: 100 | F5: Valor total Firma | G5: =B14+C14 -> 1287400
B6: 200 | F6: Valor Rossiny | G6: =B14 -> 772500 | H6: 0.6
A7: Qtidade total mesas | B7: =B3+B4+B5+B6 -> 435 | C7: =SUM(C3:C5) -> 324 | F7: Valor Petrina | G7: =C14 -> 514900 | H7: 0.4
A8: Valor por mesa | B8: 1500 | C8: 1500
A9: Total | B9: =B8*B7 -> 652500 | C9: =C8*C7 -> 486000
A10: F350 velha | B10: 40000 | C10: 0 | F10: 1287400 | G10: 100 | H10: %
A11: F350 nova | B11: 80000 | C11: 0 | F11: 514900 | G11: X
A12: Silverado | B12: 0 | C12: 28900
F13: X= | G13: =F11*G10/F10 -> 39.995339 | H13: %
A14: Total Patrimonio | B14: =SUM(B9:B11) -> 772500 | C14: =SUM(C9:C12) -> 514900
A21: Rossiny | C21: Petrina
A22: 435 mesas | C22: 324 mesas
A23: 2 caminões F350 | C23: 1 caminonete silverado
